openpifpaf-0.12.14.dist-info/RECORD
openpifpaf-0.12.14.dist-info/METADATA
openpifpaf-0.12.14.dist-info/LICENSE
openpifpaf-0.12.14.dist-info/WHEEL
openpifpaf-0.12.14.dist-info/top_level.txt
openpifpaf/stream.py
openpifpaf/utils.py
openpifpaf/logs.py
openpifpaf/video.py
openpifpaf/optimize.py
openpifpaf/conftest.py
openpifpaf/benchmark.py
openpifpaf/logger.py
openpifpaf/headmeta.py
openpifpaf/predict.py
openpifpaf/train_instance_scorer.py
openpifpaf/train.py
openpifpaf/migrate.py
openpifpaf/profiler.py
openpifpaf/functional.cpython-37m-x86_64-linux-gnu.so
openpifpaf/export_coreml.py
openpifpaf/predictor.py
openpifpaf/export_onnx.py
openpifpaf/_version.py
openpifpaf/__init__.py
openpifpaf/count_ops.py
openpifpaf/annotation.py
openpifpaf/eval.py
openpifpaf/configurable.py
openpifpaf/plugin.py
openpifpaf/visualizer/base.py
openpifpaf/visualizer/caf.py
openpifpaf/visualizer/seeds.py
openpifpaf/visualizer/cli.py
openpifpaf/visualizer/cifdet.py
openpifpaf/visualizer/cif.py
openpifpaf/visualizer/occupancy.py
openpifpaf/visualizer/cifhr.py
openpifpaf/visualizer/__init__.py
openpifpaf/network/xcit.py
openpifpaf/network/nets.py
openpifpaf/network/bottleneck_transformer.py
openpifpaf/network/trainer.py
openpifpaf/network/factory.py
openpifpaf/network/effnetv2.py
openpifpaf/network/swin_transformer.py
openpifpaf/network/__init__.py
openpifpaf/network/heads.py
openpifpaf/network/basenetworks.py
openpifpaf/network/losses/composite.py
openpifpaf/network/losses/components.py
openpifpaf/network/losses/factory.py
openpifpaf/network/losses/multi_head.py
openpifpaf/network/losses/__init__.py
openpifpaf/datasets/image_list.py
openpifpaf/datasets/collate.py
openpifpaf/datasets/multimodule.py
openpifpaf/datasets/module.py
openpifpaf/datasets/factory.py
openpifpaf/datasets/torch_dataset.py
openpifpaf/datasets/__init__.py
openpifpaf/datasets/multiloader.py
openpifpaf/show/cli.py
openpifpaf/show/annotation_painter.py
openpifpaf/show/painters.py
openpifpaf/show/animation_frame.py
openpifpaf/show/__init__.py
openpifpaf/show/fields.py
openpifpaf/show/canvas.py
openpifpaf/metric/base.py
