Metadata-Version: 2.1
Name: openpifpaf
Version: 0.12.14
Summary: PifPaf: Composite Fields for Human Pose Estimation
Home-page: https://github.com/openpifpaf/openpifpaf
Author: Sven Kreiss
Author-email: research@svenkreiss.com
License: GNU AGPLv3
Platform: UNKNOWN
Requires-Python: >=3.6
License-File: LICENSE
Requires-Dist: importlib-metadata (!=3.8.0)
Requires-Dist: numpy (>=1.16)
Requires-Dist: pysparkling
Requires-Dist: python-json-logger
Requires-Dist: torch (>=1.7.1)
Requires-Dist: torchvision (>=0.8.2)
Requires-Dist: pillow (!=8.3.0)
Requires-Dist: dataclasses ; python_version < "3.7"
Provides-Extra: backbones
Requires-Dist: timm (>=0.4.9) ; extra == 'backbones'
Requires-Dist: einops (>=0.3) ; extra == 'backbones'
Provides-Extra: coreml
Requires-Dist: coremltools (>=4.1) ; extra == 'coreml'
Provides-Extra: dev
Requires-Dist: cython ; extra == 'dev'
Requires-Dist: flameprof ; extra == 'dev'
Requires-Dist: jupyter-book (>=0.9.1) ; extra == 'dev'
Requires-Dist: matplotlib (>=3.3) ; extra == 'dev'
Requires-Dist: nbdime ; extra == 'dev'
Requires-Dist: nbstripout ; extra == 'dev'
Requires-Dist: scipy ; extra == 'dev'
Requires-Dist: sphinx-book-theme ; extra == 'dev'
Requires-Dist: wheel ; extra == 'dev'
Provides-Extra: onnx
Requires-Dist: onnx ; extra == 'onnx'
Requires-Dist: onnxruntime ; extra == 'onnx'
Requires-Dist: onnx-simplifier (>=0.2.9) ; (python_version < "3.9") and extra == 'onnx'
Provides-Extra: test
Requires-Dist: nbconvert ; extra == 'test'
Requires-Dist: nbstripout ; extra == 'test'
Requires-Dist: nbval ; extra == 'test'
Requires-Dist: onnx ; extra == 'test'
Requires-Dist: onnxruntime ; extra == 'test'
Requires-Dist: pylint (<2.9.4) ; extra == 'test'
Requires-Dist: pycodestyle ; extra == 'test'
Requires-Dist: pytest ; extra == 'test'
Requires-Dist: opencv-python ; extra == 'test'
Requires-Dist: thop ; extra == 'test'
Requires-Dist: onnx-simplifier (>=0.2.9) ; (python_version < "3.9") and extra == 'test'
Provides-Extra: train
Requires-Dist: matplotlib (>=3.3) ; extra == 'train'
Requires-Dist: pycocotools (>=2.0.1) ; extra == 'train'
Requires-Dist: scipy ; extra == 'train'
Requires-Dist: xtcocotools (>=1.5) ; (sys_platform == "linux") and extra == 'train'
